edblpy/__init__.py
edblpy/bots.py
edblpy/users.py
edblpy-1.4.0.dist-info/METADATA
edblpy-1.4.0.dist-info/WHEEL
edblpy-1.4.0.dist-info/top_level.txt
edblpy-1.4.0.dist-info/RECORD
