Metadata-Version: 2.1
Name: edblpy
Version: 1.4.0
Summary: A simple and easy-to-use unofficial python wrapper around the Electro discord bot list api
Home-page: https://github.com/Jakeisbored/edblpy
Author: Jake
Author-email: jstyle07072004@gmail.com
License: MIT
Download-URL: https://github.com/Jakeisbored/edblpy
Keywords: edbl,discord,botlist
Platform: UNKNOWN
Classifier: Development Status :: 3 - Alpha
Classifier: Intended Audience :: Developers
Classifier: Topic :: Software Development :: Build Tools
Classifier: License :: OSI Approved :: MIT License
Classifier: Programming Language :: Python :: 3
Classifier: Programming Language :: Python :: 3.4
Classifier: Programming Language :: Python :: 3.5
Classifier: Programming Language :: Python :: 3.6
Requires-Dist: requests
